aolney_jupyterlab_blockly_r_extension/__init__.py
aolney_jupyterlab_blockly_r_extension/_version.py
aolney_jupyterlab_blockly_r_extension-0.1.3.data/data/share/jupyter/labextensions/@aolney/jupyterlab-blockly-r-extension/package.json
aolney_jupyterlab_blockly_r_extension-0.1.3.data/data/share/jupyter/labextensions/@aolney/jupyterlab-blockly-r-extension/static/369.02184f958ba98de69fb9.js
aolney_jupyterlab_blockly_r_extension-0.1.3.data/data/share/jupyter/labextensions/@aolney/jupyterlab-blockly-r-extension/static/369.02184f958ba98de69fb9.js.LICENSE.txt
aolney_jupyterlab_blockly_r_extension-0.1.3.data/data/share/jupyter/labextensions/@aolney/jupyterlab-blockly-r-extension/static/728.fab96543eb438ca8425a.js
aolney_jupyterlab_blockly_r_extension-0.1.3.data/data/share/jupyter/labextensions/@aolney/jupyterlab-blockly-r-extension/static/978.1b37ca77cca964beca89.js
aolney_jupyterlab_blockly_r_extension-0.1.3.data/data/share/jupyter/labextensions/@aolney/jupyterlab-blockly-r-extension/static/978.1b37ca77cca964beca89.js.LICENSE.txt
aolney_jupyterlab_blockly_r_extension-0.1.3.data/data/share/jupyter/labextensions/@aolney/jupyterlab-blockly-r-extension/static/983.e6daa4ad1ba05ddae851.js
aolney_jupyterlab_blockly_r_extension-0.1.3.data/data/share/jupyter/labextensions/@aolney/jupyterlab-blockly-r-extension/static/983.e6daa4ad1ba05ddae851.js.LICENSE.txt
aolney_jupyterlab_blockly_r_extension-0.1.3.data/data/share/jupyter/labextensions/@aolney/jupyterlab-blockly-r-extension/static/remoteEntry.8bc064d9b088fd0815cf.js
aolney_jupyterlab_blockly_r_extension-0.1.3.data/data/share/jupyter/labextensions/@aolney/jupyterlab-blockly-r-extension/static/style.js
aolney_jupyterlab_blockly_r_extension-0.1.3.data/data/share/jupyter/labextensions/@aolney/jupyterlab-blockly-r-extension/static/third-party-licenses.json
aolney_jupyterlab_blockly_r_extension-0.1.3.data/data/share/jupyter/labextensions/@aolney/jupyterlab-blockly-r-extension/install.json
aolney_jupyterlab_blockly_r_extension-0.1.3.dist-info/METADATA
aolney_jupyterlab_blockly_r_extension-0.1.3.dist-info/WHEEL
aolney_jupyterlab_blockly_r_extension-0.1.3.dist-info/licenses/LICENSE
aolney_jupyterlab_blockly_r_extension-0.1.3.dist-info/RECORD
