Metadata-Version: 2.3
Name: aolney_jupyterlab_blockly_r_extension
Version: 0.1.3
Dynamic: Keywords
Summary: A JupyterLab extension that creates a Blockly palette for R.
Project-URL: Homepage, https://github.com/aolney/jupyterlab-blockly-r-extension
Project-URL: Bug Tracker, https://github.com/aolney/jupyterlab-blockly-r-extension/issues
Project-URL: Repository, https://github.com/aolney/jupyterlab-blockly-r-extension.git
Author-email: "Andrew M. Olney" <aolney@memphis.edu>
License:                                  Apache License
License-File: LICENSE
Classifier: Framework :: Jupyter
Classifier: Framework :: Jupyter :: JupyterLab
Classifier: Framework :: Jupyter :: JupyterLab :: 4
Classifier: Framework :: Jupyter :: JupyterLab :: Extensions
Classifier: Framework :: Jupyter :: JupyterLab :: Extensions :: Prebuilt
Classifier: License :: OSI Approved :: BSD License
Classifier: Programming Language :: Python
Classifier: Programming Language :: Python :: 3
Classifier: Programming Language :: Python :: 3.8
Classifier: Programming Language :: Python :: 3.9
Classifier: Programming Language :: Python :: 3.10
Classifier: Programming Language :: Python :: 3.11
Classifier: Programming Language :: Python :: 3.12
Requires-Python: >=3.8
